typing_environs/__init__.py
typing_environs/environment.py
typing_environs-0.3.0.dist-info/LICENSE
typing_environs-0.3.0.dist-info/LICENSE.md
typing_environs-0.3.0.dist-info/WHEEL
typing_environs-0.3.0.dist-info/METADATA
typing_environs-0.3.0.dist-info/RECORD
